airflow_provider_datarobot-1.0.2.dist-info/licenses/LICENSE
datarobot_provider/__init__.py
datarobot_provider/_version.py
datarobot_provider/constants.py
datarobot_provider/py.typed
datarobot_provider/autogen/__init__.py
datarobot_provider/autogen/generate_operator.py
datarobot_provider/example_dags/__init__.py
datarobot_provider/example_dags/dataprep_wrangler_autopilot.py
datarobot_provider/example_dags/datarobot_run_notebook.py
datarobot_provider/example_dags/deployment_prediction_generation.py
datarobot_provider/example_dags/feature_discovery_example.py
datarobot_provider/example_dags/feature_discovery_retraining_and_scoring.py
datarobot_provider/example_dags/model_training_xgboost.py
datarobot_provider/example_dags/post_predictions_formatting.py
datarobot_provider/example_dags/wrangler_example_recipe.py
datarobot_provider/hooks/__init__.py
datarobot_provider/hooks/datarobot.py
datarobot_provider/operators/__init__.py
datarobot_provider/operators/autopilot.py
datarobot_provider/operators/base_datarobot_operator.py
datarobot_provider/operators/bias_and_fairness.py
datarobot_provider/operators/custom_function.py
datarobot_provider/operators/custom_models.py
datarobot_provider/operators/data_prep.py
datarobot_provider/operators/data_registry.py
datarobot_provider/operators/datarobot.py
datarobot_provider/operators/deployment.py
datarobot_provider/operators/mlops.py
datarobot_provider/operators/model_insights.py
datarobot_provider/operators/model_package.py
datarobot_provider/operators/model_predictions.py
datarobot_provider/operators/model_registry.py
datarobot_provider/operators/model_training.py
datarobot_provider/operators/monitoring.py
datarobot_provider/operators/monitoring_job.py
datarobot_provider/operators/notebook.py
datarobot_provider/operators/prediction_explanations.py
datarobot_provider/operators/predictions.py
datarobot_provider/operators/queue.py
datarobot_provider/operators/scoring_code.py
datarobot_provider/operators/segment_analysis.py
datarobot_provider/operators/segmentation.py
airflow_provider_datarobot-1.0.2.dist-info/METADATA
airflow_provider_datarobot-1.0.2.dist-info/WHEEL
airflow_provider_datarobot-1.0.2.dist-info/entry_points.txt
airflow_provider_datarobot-1.0.2.dist-info/top_level.txt
airflow_provider_datarobot-1.0.2.dist-info/RECORD
